[{"id":0,"href":"/mercury-modding-wiki/","title":"","parent":"","content":"","description":""},{"id":1,"href":"/mercury-modding-wiki/formats/","title":"Formats","parent":"","content":"Various mercury engine formats\n","description":"Various mercury engine formats"},{"id":2,"href":"/mercury-modding-wiki/formats/bccam/","title":"Bccam","parent":"Formats","content":"WIP\n","description":"WIP"},{"id":3,"href":"/mercury-modding-wiki/formats/bclgt/","title":"Bclgt","parent":"Formats","content":"WIP\n","description":"WIP"},{"id":4,"href":"/mercury-modding-wiki/formats/bcmdl/","title":"Bcmdl","parent":"Formats","content":"WIP\n","description":"WIP"},{"id":5,"href":"/mercury-modding-wiki/formats/bcptl/","title":"Bcptl","parent":"Formats","content":"WIP\n","description":"WIP"},{"id":6,"href":"/mercury-modding-wiki/formats/bcskla/","title":"Bcskla","parent":"Formats","content":"WIP\n","description":"WIP"},{"id":7,"href":"/mercury-modding-wiki/formats/bctex/","title":"Bctex","parent":"Formats","content":"WIP\n","description":"WIP"},{"id":8,"href":"/mercury-modding-wiki/formats/bcut/","title":"Bcut","parent":"Formats","content":"WIP\n","description":"WIP"},{"id":9,"href":"/mercury-modding-wiki/formats/bcwav/","title":"Bcwav","parent":"Formats","content":"WIP\n","description":"WIP"},{"id":10,"href":"/mercury-modding-wiki/formats/bfont/","title":"Bfont","parent":"Formats","content":"WIP\n","description":"WIP"},{"id":11,"href":"/mercury-modding-wiki/formats/blsnd/","title":"Blsnd","parent":"Formats","content":"WIP\n","description":"WIP"},{"id":12,"href":"/mercury-modding-wiki/formats/bmdefs/","title":"Bmdefs","parent":"Formats","content":"WIP\n","description":"WIP"},{"id":13,"href":"/mercury-modding-wiki/formats/bmsad/","title":"Bmsad","parent":"Formats","content":"WIP\n","description":"WIP"},{"id":14,"href":"/mercury-modding-wiki/formats/bmsat/","title":"Bmsat","parent":"Formats","content":"WIP\n","description":"WIP"},{"id":15,"href":"/mercury-modding-wiki/formats/bmsbk/","title":"Bmsbk","parent":"Formats","content":"WIP\n","description":"WIP"},{"id":16,"href":"/mercury-modding-wiki/formats/bmscc/","title":"Bmscc","parent":"Formats","content":"WIP\n","description":"WIP"},{"id":17,"href":"/mercury-modding-wiki/formats/bmscd/","title":"Bmscd","parent":"Formats","content":"WIP\n","description":"WIP"},{"id":18,"href":"/mercury-modding-wiki/formats/bmscu/","title":"Bmscu","parent":"Formats","content":"WIP\n","description":"WIP"},{"id":19,"href":"/mercury-modding-wiki/formats/bmsem/","title":"Bmsem","parent":"Formats","content":"WIP\n","description":"WIP"},{"id":20,"href":"/mercury-modding-wiki/formats/bmses/","title":"Bmses","parent":"Formats","content":"WIP\n","description":"WIP"},{"id":21,"href":"/mercury-modding-wiki/formats/bmsev/","title":"Bmsev","parent":"Formats","content":"WIP\n","description":"WIP"},{"id":22,"href":"/mercury-modding-wiki/formats/bmsld/","title":"Bmsld","parent":"Formats","content":"WIP\n","description":"WIP"},{"id":23,"href":"/mercury-modding-wiki/formats/bmsmd/","title":"Bmsmd","parent":"Formats","content":"WIP\n","description":"WIP"},{"id":24,"href":"/mercury-modding-wiki/formats/bmsmsd/","title":"Bmsmsd","parent":"Formats","content":"WIP\n","description":"WIP"},{"id":25,"href":"/mercury-modding-wiki/formats/bmsnav/","title":"Bmsnav","parent":"Formats","content":"WIP\n","description":"WIP"},{"id":26,"href":"/mercury-modding-wiki/formats/bmsnd/","title":"Bmsnd","parent":"Formats","content":"WIP\n","description":"WIP"},{"id":27,"href":"/mercury-modding-wiki/formats/bmssa/","title":"Bmssa","parent":"Formats","content":"WIP\n","description":"WIP"},{"id":28,"href":"/mercury-modding-wiki/formats/bmssd/","title":"Bmssd","parent":"Formats","content":"WIP\n","description":"WIP"},{"id":29,"href":"/mercury-modding-wiki/formats/bmtre/","title":"Bmtre","parent":"Formats","content":"WIP\n","description":"WIP"},{"id":30,"href":"/mercury-modding-wiki/formats/bmtun/","title":"Bmtun","parent":"Formats","content":"WIP\n","description":"WIP"},{"id":31,"href":"/mercury-modding-wiki/formats/bpsi/","title":"Bpsi","parent":"Formats","content":"WIP\n","description":"WIP"},{"id":32,"href":"/mercury-modding-wiki/formats/buct/","title":"Buct","parent":"Formats","content":"WIP\n","description":"WIP"},{"id":33,"href":"/mercury-modding-wiki/tags/","title":"Tags","parent":"","content":"","description":""}]